Workbook

Sheet Assumptions
A1: Video Art Members' Collection: Assumptions
A2: Blue = editable input. Yellow = key lever. All figures are illustrative assumptions by Claude, not sourced data; replace with your own.
A4: Input | B4: Value
A5: Scenario (1 = Low, 2 = Base, 3 = High) | B5: 2
A6: Monthly membership price ($) | B6: 12
A7: Annual churn (% of opening members) | B7: 0.35
A8: Payment / app-store fees (% of gross) | B8: 0.08
A9: Artist streaming licence pool (% of net revenue) | B9: 0.2
A10: Acquisition fund (% of net revenue) | B10: 0.25
A11: Share of fund spent buying existing editions | B11: 0.7
A12: Average price of a video edition ($) | B12: 60000
A13: Average cost of a new commission ($) | B13: 40000
A14: Platform & tech costs per year ($) | B14: 600000
A15: Staff & curation costs per year ($) | B15: 800000
A16: Marketing cost per new member ($) | B16: 40
A17: Loan / screening fee per collection work per year ($) | B17: 1500
A19: New members acquired per year
A20: Scenario | B20: Year 1 | C20: Year 2 | D20: Year 3 | E20: Year 4 | F20: Year 5
A21: Low | B21: 5000 | C21: 7000 | D21: 9000 | E21: 10000 | F21: 11000
A22: Base | B22: 15000 | C22: 20000 | D22: 25000 | E22: 30000 | F22: 35000
A23: High | B23: 40000 | C23: 60000 | D23: 80000 | E23: 90000 | F23: 100000
A25: Basis: Low ≈ art-world core only; Base ≈ core plus some culture-curious viewers; High ≈ MUBI-style breakout or a bundle with a magazine/fair. Illustrative.

Sheet Model
A1: Five-Year Model
A2: ="Scenario: "&INDEX({"Low","Base","High"},Assumptions!$B$5) -> Scenario: Base
A4: ($, members) | B4: Year 1 | C4: Year 2 | D4: Year 3 | E4: Year 4 | F4: Year 5
A5: MEMBERS
A6: Opening members | B6: =0 -> 0 | C6: =B9 -> 15000 | D6: =C9 -> 29750 | E6: =D9 -> 44337.5 | F6: =E9 -> 58819.375
A7: New members | B7: =INDEX(Assumptions!B$21:B$23,Assumptions!$B$5) -> 15000 | C7: =INDEX(Assumptions!C$21:C$23,Assumptions!$B$5) -> 20000 | D7: =INDEX(Assumptions!D$21:D$23,Assumptions!$B$5) -> 25000 | E7: =INDEX(Assumptions!E$21:E$23,Assumptions!$B$5) -> 30000 | F7: =INDEX(Assumptions!F$21:F$23,Assumptions!$B$5) -> 35000
A8: Churned members | B8: =-B6*Assumptions!$B$7 -> 0 | C8: =-C6*Assumptions!$B$7 -> -5250 | D8: =-D6*Assumptions!$B$7 -> -10412.5 | E8: =-E6*Assumptions!$B$7 -> -15518.125 | F8: =-F6*Assumptions!$B$7 -> -20586.781
A9: Closing members | B9: =B6+B7+B8 -> 15000 | C9: =C6+C7+C8 -> 29750 | D9: =D6+D7+D8 -> 44337.5 | E9: =E6+E7+E8 -> 58819.375 | F9: =F6+F7+F8 -> 73232.594
A10: Average paying members | B10: =(B6+B9)/2 -> 7500 | C10: =(C6+C9)/2 -> 22375 | D10: =(D6+D9)/2 -> 37043.75 | E10: =(E6+E9)/2 -> 51578.438 | F10: =(F6+F9)/2 -> 66025.984
A12: REVENUE
A13: Gross membership revenue | B13: =B10*Assumptions!$B$6*12 -> 1080000 | C13: =C10*Assumptions!$B$6*12 -> 3222000 | D13: =D10*Assumptions!$B$6*12 -> 5334300 | E13: =E10*Assumptions!$B$6*12 -> 7427295 | F13: =F10*Assumptions!$B$6*12 -> 9507741.8
A14: Payment / app-store fees | B14: =-B13*Assumptions!$B$8 -> -86400 | C14: =-C13*Assumptions!$B$8 -> -257760 | D14: =-D13*Assumptions!$B$8 -> -426744 | E14: =-E13*Assumptions!$B$8 -> -594183.6 | F14: =-F13*Assumptions!$B$8 -> -760619.34
A15: Net membership revenue | B15: =B13+B14 -> 993600 | C15: =C13+C14 -> 2964240 | D15: =D13+D14 -> 4907556 | E15: =E13+E14 -> 6833111.4 | F15: =F13+F14 -> 8747122.4
A16: Loan / screening income | B16: =0 -> 0 | C16: =B35*Assumptions!$B$17 -> 4500 | D16: =C35*Assumptions!$B$17 -> 27000 | E16: =D35*Assumptions!$B$17 -> 61500 | F16: =E35*Assumptions!$B$17 -> 111000
A17: Total income | B17: =B15+B16 -> 993600 | C17: =C15+C16 -> 2968740 | D17: =D15+D16 -> 4934556 | E17: =E15+E16 -> 6894611.4 | F17: =F15+F16 -> 8858122.4
A19: COSTS
A20: Artist streaming licence pool | B20: =-B15*Assumptions!$B$9 -> -198720 | C20: =-C15*Assumptions!$B$9 -> -592848 | D20: =-D15*Assumptions!$B$9 -> -981511.2 | E20: =-E15*Assumptions!$B$9 -> -1366622.3 | F20: =-F15*Assumptions!$B$9 -> -1749424.5
A21: Platform & tech | B21: =-Assumptions!$B$14 -> -600000 | C21: =-Assumptions!$B$14 -> -600000 | D21: =-Assumptions!$B$14 -> -600000 | E21: =-Assumptions!$B$14 -> -600000 | F21: =-Assumptions!$B$14 -> -600000
A22: Staff & curation | B22: =-Assumptions!$B$15 -> -800000 | C22: =-Assumptions!$B$15 -> -800000 | D22: =-Assumptions!$B$15 -> -800000 | E22: =-Assumptions!$B$15 -> -800000 | F22: =-Assumptions!$B$15 -> -800000
A23: Marketing (new members) | B23: =-B7*Assumptions!$B$16 -> -600000 | C23: =-C7*Assumptions!$B$16 -> -800000 | D23: =-D7*Assumptions!$B$16 -> -1000000 | E23: =-E7*Assumptions!$B$16 -> -1200000 | F23: =-F7*Assumptions!$B$16 -> -1400000
A24: Operating result before acquisitions | B24: =B17+B20+B21+B22+B23 -> -1205120 | C24: =C17+C20+C21+C22+C23 -> 175892 | D24: =D17+D20+D21+D22+D23 -> 1553044.8 | E24: =E17+E20+E21+E22+E23 -> 2927989.1 | F24: =F17+F20+F21+F22+F23 -> 4308697.9
A25: Acquisition fund contribution | B25: =-B15*Assumptions!$B$10 -> -248400 | C25: =-C15*Assumptions!$B$10 -> -741060 | D25: =-D15*Assumptions!$B$10 -> -1226889 | E25: =-E15*Assumptions!$B$10 -> -1708277.9 | F25: =-F15*Assumptions!$B$10 -> -2186780.6
A26: Net result after acquisitions | B26: =B24+B25 -> -1453520 | C26: =C24+C25 -> -565168 | D26: =D24+D25 -> 326155.8 | E26: =E24+E25 -> 1219711.3 | F26: =F24+F25 -> 2121917.3
A27: Cumulative net result | B27: =B26 -> -1453520 | C27: =B27+C26 -> -2018688 | D27: =C27+D26 -> -1692532.2 | E27: =D27+E26 -> -472820.93 | F27: =E27+F26 -> 1649096.4
A29: COLLECTION
A30: Fund available (incl. unspent carry-over) | B30: =-B25 -> 248400 | C30: =-C25+B34 -> 829460 | D30: =-D25+C34 -> 1276349 | E30: =-E25+D34 -> 1784626.9 | F30: =-F25+E34 -> 2251407.5
A31: Editions bought | B31: =INT(B30*Assumptions!$B$11/Assumptions!$B$12) -> 2 | C31: =INT(C30*Assumptions!$B$11/Assumptions!$B$12) -> 9 | D31: =INT(D30*Assumptions!$B$11/Assumptions!$B$12) -> 14 | E31: =INT(E30*Assumptions!$B$11/Assumptions!$B$12) -> 20 | F31: =INT(F30*Assumptions!$B$11/Assumptions!$B$12) -> 26
A32: New commissions | B32: =INT(B30*(1-Assumptions!$B$11)/Assumptions!$B$13) -> 1 | C32: =INT(C30*(1-Assumptions!$B$11)/Assumptions!$B$13) -> 6 | D32: =INT(D30*(1-Assumptions!$B$11)/Assumptions!$B$13) -> 9 | E32: =INT(E30*(1-Assumptions!$B$11)/Assumptions!$B$13) -> 13 | F32: =INT(F30*(1-Assumptions!$B$11)/Assumptions!$B$13) -> 16
A33: Spent this year | B33: =B31*Assumptions!$B$12+B32*Assumptions!$B$13 -> 160000 | C33: =C31*Assumptions!$B$12+C32*Assumptions!$B$13 -> 780000 | D33: =D31*Assumptions!$B$12+D32*Assumptions!$B$13 -> 1200000 | E33: =E31*Assumptions!$B$12+E32*Assumptions!$B$13 -> 1720000 | F33: =F31*Assumptions!$B$12+F32*Assumptions!$B$13 -> 2200000
A34: Unspent carried forward | B34: =B30-B33 -> 88400 | C34: =C30-C33 -> 49460 | D34: =D30-D33 -> 76349 | E34: =E30-E33 -> 64626.85 | F34: =F30-F33 -> 51407.453
A35: Works in collection (cumulative) | B35: =B31+B32 -> 3 | C35: =B35+C31+C32 -> 18 | D35: =C35+D31+D32 -> 41 | E35: =D35+E31+E32 -> 74 | F35: =E35+F31+F32 -> 116
A36: Collection at cost (cumulative) | B36: =B33 -> 160000 | C36: =B36+C33 -> 940000 | D36: =C36+D33 -> 2140000 | E36: =D36+E33 -> 3860000 | F36: =E36+F33 -> 6060000
A38: KEY METRICS
A39: Annual payout to artists (licence + acquisitions spent) | B39: =-B20+B33 -> 358720 | C39: =-C20+C33 -> 1372848 | D39: =-D20+D33 -> 2181511.2 | E39: =-E20+E33 -> 3086622.3 | F39: =-F20+F33 -> 3949424.5
A40: Break-even members (before acquisitions) | B40: =(Assumptions!$B$14+Assumptions!$B$15)/(Assumptions!$B$6*12*(1-Assumptions!$B$8)*(1-Assumptions!$B$9)) -> 13209.541 | C40: =(Assumptions!$B$14+Assumptions!$B$15)/(Assumptions!$B$6*12*(1-Assumptions!$B$8)*(1-Assumptions!$B$9)) -> 13209.541 | D40: =(Assumptions!$B$14+Assumptions!$B$15)/(Assumptions!$B$6*12*(1-Assumptions!$B$8)*(1-Assumptions!$B$9)) -> 13209.541 | E40: =(Assumptions!$B$14+Assumptions!$B$15)/(Assumptions!$B$6*12*(1-Assumptions!$B$8)*(1-Assumptions!$B$9)) -> 13209.541 | F40: =(Assumptions!$B$14+Assumptions!$B$15)/(Assumptions!$B$6*12*(1-Assumptions!$B$8)*(1-Assumptions!$B$9)) -> 13209.541
A41: Break-even members (after acquisitions) | B41: =(Assumptions!$B$14+Assumptions!$B$15)/(Assumptions!$B$6*12*(1-Assumptions!$B$8)*(1-Assumptions!$B$9-Assumptions!$B$10)) -> 19213.878 | C41: =(Assumptions!$B$14+Assumptions!$B$15)/(Assumptions!$B$6*12*(1-Assumptions!$B$8)*(1-Assumptions!$B$9-Assumptions!$B$10)) -> 19213.878 | D41: =(Assumptions!$B$14+Assumptions!$B$15)/(Assumptions!$B$6*12*(1-Assumptions!$B$8)*(1-Assumptions!$B$9-Assumptions!$B$10)) -> 19213.878 | E41: =(Assumptions!$B$14+Assumptions!$B$15)/(Assumptions!$B$6*12*(1-Assumptions!$B$8)*(1-Assumptions!$B$9-Assumptions!$B$10)) -> 19213.878 | F41: =(Assumptions!$B$14+Assumptions!$B$15)/(Assumptions!$B$6*12*(1-Assumptions!$B$8)*(1-Assumptions!$B$9-Assumptions!$B$10)) -> 19213.878

Sheet Notes
A1: How to use
A2: 1. Change blue cells on the Assumptions sheet; yellow cells are the main levers.
A3: 2. Switch scenario with Assumptions!B5 (1 Low, 2 Base, 3 High).
A4: 3. The Model sheet recalculates everything: members, revenue, costs, and how many works the fund buys.
A6: Simplifications
A7: - Annual model; churn applied to opening members only (new joiners assumed to stay their first year).
A8: - No tax, VAT, financing, or rights-clearance legal costs; no resale of collection works.
A9: - Collection valued at cost; video editions often resell below cost, so treat this as an upper bound.
A10: - Streaming rights for owned editions are assumed covered by the licence pool; in practice each needs negotiating.
A11: - Every input is an illustrative assumption, not sourced market data.
